["{\"score\":\"0\",\"subType\":\"0\",\"ID\":\"100010001\",\"time\":\"0\",\"blood\":\"10\"}","{\"score\":\"0\",\"subType\":\"0\",\"ID\":\"100010002\",\"time\":\"0\",\"blood\":\"30\"}","{\"score\":\"10\",\"subType\":\"1\",\"ID\":\"500030002\",\"time\":\"0\",\"blood\":\"0\"}","{\"score\":\"10\",\"subType\":\"1\",\"ID\":\"500030005\",\"time\":\"0\",\"blood\":\"0\"}","{\"score\":\"10\",\"subType\":\"1\",\"ID\":\"500030008\",\"time\":\"0\",\"blood\":\"0\"}","{\"score\":\"10\",\"subType\":\"1\",\"ID\":\"500030011\",\"time\":\"0\",\"blood\":\"0\"}","{\"score\":\"10\",\"subType\":\"1\",\"ID\":\"500030016\",\"time\":\"0\",\"blood\":\"0\"}","{\"score\":\"10\",\"subType\":\"1\",\"ID\":\"500030021\",\"time\":\"0\",\"blood\":\"0\"}","{\"score\":\"10\",\"subType\":\"1\",\"ID\":\"500030024\",\"time\":\"0\",\"blood\":\"0\"}","{\"score\":\"10\",\"subType\":\"1\",\"ID\":\"500030027\",\"time\":\"0\",\"blood\":\"0\"}","{\"score\":\"10\",\"subType\":\"1\",\"ID\":\"500030030\",\"time\":\"0\",\"blood\":\"0\"}","{\"score\":\"10\",\"subType\":\"1\",\"ID\":\"500030035\",\"time\":\"0\",\"blood\":\"0\"}","{\"score\":\"10\",\"subType\":\"2\",\"ID\":\"270030001\",\"time\":\"0\",\"blood\":\"0\"}","{\"score\":\"10\",\"subType\":\"2\",\"ID\":\"270030002\",\"time\":\"0\",\"blood\":\"0\"}","{\"score\":\"10\",\"subType\":\"2\",\"ID\":\"270030003\",\"time\":\"0\",\"blood\":\"0\"}","{\"score\":\"10\",\"subType\":\"2\",\"ID\":\"270030004\",\"time\":\"0\",\"blood\":\"0\"}","{\"score\":\"10\",\"subType\":\"2\",\"ID\":\"270030005\",\"time\":\"0\",\"blood\":\"0\"}","{\"score\":\"10\",\"subType\":\"3\",\"ID\":\"800020001\",\"time\":\"0\",\"blood\":\"0\"}","{\"score\":\"10\",\"subType\":\"3\",\"ID\":\"800020002\",\"time\":\"0\",\"blood\":\"0\"}","{\"score\":\"10\",\"subType\":\"3\",\"ID\":\"800020003\",\"time\":\"0\",\"blood\":\"0\"}","{\"score\":\"10\",\"subType\":\"3\",\"ID\":\"800020004\",\"time\":\"0\",\"blood\":\"0\"}","{\"score\":\"10\",\"subType\":\"3\",\"ID\":\"800020005\",\"time\":\"0\",\"blood\":\"0\"}","{\"score\":\"10\",\"subType\":\"4\",\"ID\":\"260030001\",\"time\":\"0\",\"blood\":\"0\"}","{\"score\":\"10\",\"subType\":\"4\",\"ID\":\"260030002\",\"time\":\"0\",\"blood\":\"0\"}","{\"score\":\"10\",\"subType\":\"4\",\"ID\":\"260030003\",\"time\":\"0\",\"blood\":\"0\"}","{\"score\":\"10\",\"subType\":\"5\",\"ID\":\"909990001\",\"time\":\"0\",\"blood\":\"0\"}","{\"score\":\"10\",\"subType\":\"5\",\"ID\":\"909990002\",\"time\":\"0\",\"blood\":\"0\"}","{\"score\":\"10\",\"subType\":\"5\",\"ID\":\"909990003\",\"time\":\"0\",\"blood\":\"0\"}"]